dynamoclasses/__init__.py
dynamoclasses/test/__init__.py
dynamoclasses/test/test_dynamoclasses.py
dynamoclasses-1.0.0a2.dist-info/METADATA
dynamoclasses-1.0.0a2.dist-info/WHEEL
dynamoclasses-1.0.0a2.dist-info/top_level.txt
dynamoclasses-1.0.0a2.dist-info/RECORD
