Metadata-Version: 2.1
Name: dynamoclasses
Version: 1.0.0a2
Summary: DynamoDB ORM using dataclasses
Home-page: https://github.com/ewdurbin/dynamoclasses
Author: Ee Durbin
Author-email: ewdurbin@gmail.com
License: UNKNOWN
Project-URL: Source, https://github.com/ewdurbin/dynamoclasses/
Project-URL: Bug Reports, https://github.com/ewdurbin/dynamoclasses/issues
Keywords: dataclasses dynamodb
Platform: UNKNOWN
Classifier: Development Status :: 3 - Alpha
Classifier: Intended Audience :: Developers
Classifier: Programming Language :: Python :: 3.7
Requires-Dist: boto3
Requires-Dist: dataclasses
Provides-Extra: test
Requires-Dist: moto ; extra == 'test'
